yTermPlayer/__init__.py
yTermPlayer/__main__.py
yTermPlayer/music_api.py
yTermPlayer/settings.py
yTermPlayer/test.py
yTermPlayer/ui.py
yTermPlayer/yterm-player.py
yTermPlayer-1.2.2.dist-info/LICENSE
yTermPlayer-1.2.2.dist-info/METADATA
yTermPlayer-1.2.2.dist-info/WHEEL
yTermPlayer-1.2.2.dist-info/entry_points.txt
yTermPlayer-1.2.2.dist-info/top_level.txt
yTermPlayer-1.2.2.dist-info/RECORD
