Metadata-Version: 2.1
Name: yTermPlayer
Version: 1.2.2
Summary: Stream youtube playlists as audio on linux terminal 
Home-page: https://github.com/TimeTraveller-San/yTermPlayer
Author: Time Traveller
Author-email: time.traveller.san@gmail.com
License: GPLv3
Platform: UNKNOWN
Classifier: Programming Language :: Python :: 3
Classifier: Operating System :: POSIX :: Linux
Requires-Python: >=3
Requires-Dist: pafy (>=0.5.4)
Requires-Dist: python-dateutil (>=2.7.5)
Requires-Dist: python-mpv (>=0.3.9)
Requires-Dist: urwid (>=2.0.1)
Requires-Dist: virtualenv (>=16.0.0)
Requires-Dist: youtube-dl (>=2019.5.20)
